HISTORY.rst
LICENSE
MANIFEST.in
README.rst
requirements.txt
setup.py
docraptor/__init__.py
python_docraptor.egg-info/PKG-INFO
python_docraptor.egg-info/SOURCES.txt
python_docraptor.egg-info/dependency_links.txt
python_docraptor.egg-info/requires.txt
python_docraptor.egg-info/top_level.txt