Metadata-Version: 1.0
Name: python-docraptor
Version: 1.2.1
Summary: Doc Raptor API wrapper
Home-page: http://github.com/jkeyes/python-docraptor
Author: John Keyes
Author-email: john@keyes.ie
License: MIT License
Keywords: DocRaptor pdf python
Platform: UNKNOWN
